kaiwu_community/__init__.py
kaiwu_community/classical/__init__.py
kaiwu_community/classical/_brute_force.py
kaiwu_community/common/__init__.py
kaiwu_community/common/_logger.py
kaiwu_community/common/_util.py
kaiwu_community/conversion/__init__.py
kaiwu_community/conversion/_matrix_converter.py
kaiwu_community/conversion/_model_converter.py
kaiwu_community/core/__init__.py
kaiwu_community/core/_binary_expression.py
kaiwu_community/core/_binary_model.py
kaiwu_community/core/_constraint.py
kaiwu_community/core/_error.py
kaiwu_community/core/_expression.py
kaiwu_community/core/_get_val.py
kaiwu_community/core/_matrix.py
kaiwu_community/core/_optimizer_base.py
kaiwu_community/core/_penalty_method_constraint.py
kaiwu_community/core/_solver_base.py
kaiwu_community/ising/__init__.py
kaiwu_community/ising/_ising.py
kaiwu_community/ising/_precision.py
kaiwu_community/qubo/__init__.py
kaiwu_community/qubo/_error.py
kaiwu_community/qubo/_precision.py
kaiwu_community/qubo/_qubo_model.py
kaiwu_community/qubo/_repr.py
kaiwu_community/solver/__init__.py
kaiwu_community/solver/_simple_solver.py
kaiwu_community-1.0.3.dist-info/licenses/LICENSE
kaiwu_community-1.0.3.dist-info/METADATA
kaiwu_community-1.0.3.dist-info/WHEEL
kaiwu_community-1.0.3.dist-info/top_level.txt
kaiwu_community-1.0.3.dist-info/RECORD
