Metadata-Version: 2.4
Name: kaiwu_community
Version: 1.0.3
Summary: An SDK for CIM or QUBO.
Author: Qboson Inc
Project-URL: Homepage, https://kaiwu-community.readthedocs.io
Project-URL: Documentation, https://kaiwu-community.readthedocs.io
Project-URL: Source, https://github.com/qboson/kaiwu_community
Classifier: Programming Language :: Python :: 3
Classifier: Operating System :: OS Independent
Requires-Python: >=3.10
License-File: LICENSE
Requires-Dist: numpy==2.2.6
Requires-Dist: pandas==2.2.3
Dynamic: license-file
